muutils/__init__.py
muutils/collect_warnings.py
muutils/console_unicode.py
muutils/dbg.py
muutils/dictmagic.py
muutils/errormode.py
muutils/group_equiv.py
muutils/interval.py
muutils/jsonlines.py
muutils/kappa.py
muutils/mlutils.py
muutils/parallel.py
muutils/py.typed
muutils/spinner.py
muutils/statcounter.py
muutils/sysinfo.py
muutils/tensor_info.py
muutils/tensor_utils.py
muutils/timeit_fancy.py
muutils/validate_type.py
muutils/json_serialize/__init__.py
muutils/json_serialize/array.py
muutils/json_serialize/dataclass_transform_mock.py
muutils/json_serialize/json_serialize.py
muutils/json_serialize/serializable_dataclass.py
muutils/json_serialize/serializable_field.py
muutils/json_serialize/util.py
muutils/logger/__init__.py
muutils/logger/exception_context.py
muutils/logger/headerfuncs.py
muutils/logger/log_util.py
muutils/logger/logger.py
muutils/logger/loggingstream.py
muutils/logger/simplelogger.py
muutils/logger/timing.py
muutils/math/__init__.py
muutils/math/bins.py
muutils/math/matrix_powers.py
muutils/misc/__init__.py
muutils/misc/b64_decode.py
muutils/misc/classes.py
muutils/misc/freezing.py
muutils/misc/func.py
muutils/misc/hashing.py
muutils/misc/numerical.py
muutils/misc/sequence.py
muutils/misc/string.py
muutils/nbutils/__init__.py
muutils/nbutils/configure_notebook.py
muutils/nbutils/convert_ipynb_to_script.py
muutils/nbutils/mermaid.py
muutils/nbutils/print_tex.py
muutils/nbutils/run_notebook_tests.py
muutils/web/__init__.py
muutils/web/bundle_html.py
muutils-0.8.11.dist-info/METADATA
muutils-0.8.11.dist-info/WHEEL
muutils-0.8.11.dist-info/licenses/LICENSE
muutils-0.8.11.dist-info/RECORD
