Metadata-Version: 2.4
Name: muutils
Version: 0.8.11
Summary: miscellaneous python utilities
Project-URL: Homepage, https://miv.name/muutils
Project-URL: Repository, https://github.com/mivanit/muutils
Project-URL: Documentation, https://miv.name/muutils/
Project-URL: Issues, https://github.com/mivanit/muutils/issues
Author-email: mivanit <mivanits@umich.edu>
License: GPL-3.0-only
License-File: LICENSE
Classifier: Development Status :: 4 - Beta
Classifier: License :: OSI Approved :: GNU General Public License v3 (GPLv3)
Classifier: Operating System :: OS Independent
Classifier: Programming Language :: Python :: 3.8
Classifier: Programming Language :: Python :: 3.9
Classifier: Programming Language :: Python :: 3.10
Classifier: Programming Language :: Python :: 3.11
Classifier: Programming Language :: Python :: 3.12
Classifier: Programming Language :: Python :: 3.13
Classifier: Topic :: Utilities
Classifier: Typing :: Typed
Requires-Python: >=3.8
Provides-Extra: array
Requires-Dist: jaxtyping>=0.2.12; extra == 'array'
Requires-Dist: numpy>1.24.4; (python_version >= '3.9') and extra == 'array'
Requires-Dist: numpy>=1.24.4; (python_version < '3.9') and extra == 'array'
Requires-Dist: torch<2.5.0,>=1.13.1; (python_version < '3.9') and extra == 'array'
Requires-Dist: torch>=1.13.1; (python_version >= '3.9' and python_version < '3.13') and extra == 'array'
Requires-Dist: torch>=2.5.0; (python_version >= '3.13') and extra == 'array'
Provides-Extra: array-no-torch
Requires-Dist: jaxtyping>=0.2.12; extra == 'array-no-torch'
Requires-Dist: numpy>1.24.4; (python_version >= '3.9') and extra == 'array-no-torch'
Requires-Dist: numpy>=1.24.4; (python_version < '3.9') and extra == 'array-no-torch'
Provides-Extra: notebook
Requires-Dist: ipython>=8.0.0; extra == 'notebook'
Provides-Extra: parallel
Requires-Dist: multiprocess>=0.70.17; extra == 'parallel'
Requires-Dist: tqdm>=4.67.1; extra == 'parallel'
